buildout.cfg
setup.cfg
setup.py
src/ooo2tools/__init__.py
src/ooo2tools.daemon.egg-info/PKG-INFO
src/ooo2tools.daemon.egg-info/SOURCES.txt
src/ooo2tools.daemon.egg-info/dependency_links.txt
src/ooo2tools.daemon.egg-info/entry_points.txt
src/ooo2tools.daemon.egg-info/namespace_packages.txt
src/ooo2tools.daemon.egg-info/not-zip-safe
src/ooo2tools.daemon.egg-info/requires.txt
src/ooo2tools.daemon.egg-info/top_level.txt
src/ooo2tools/daemon/__init__.py
src/ooo2tools/daemon/daemon.py
src/ooo2tools/daemon/ooo2tools_daemon.py
src/ooo2tools/daemon/tests/__init__.py
src/ooo2tools/daemon/tests/test_ooo2tools_daemon.py