Metadata-Version: 1.0
Name: ooo2tools.daemon
Version: 0.1dev-r2155
Summary: a daemon processing macros using ooo2tools.core
Home-page: UNKNOWN
Author: Alexandre LE GROS
Author-email: alexandre_lg@hotmail.fr
License: UNKNOWN
Keywords: open office daemon
Platform: UNKNOWN
